{
    "affycoretools": [
        "ReportingTools",
        "VariantAnnotation",
        "biovizBase",
        "ggbio"
    ],
    "AgiMicroRna": [
        "ReportingTools",
        "VariantAnnotation",
        "affycoretools",
        "biovizBase",
        "ggbio"
    ],
    "AHMassBank": [
        "AnnotationHubData"
    ],
    "alabaster": [
        "VariantAnnotation",
        "alabaster.vcf"
    ],
    "alabaster.vcf": [
        "VariantAnnotation"
    ],
    "AllelicImbalance": [
        "Gviz",
        "VariantAnnotation",
        "biovizBase"
    ],
    "AnnotationHubData": [],
    "annotatr": [],
    "APAlyzer": [
        "VariantAnnotation"
    ],
    "appreci8R": [
        "VariantAnnotation"
    ],
    "arrayMvout": [
        "lumi",
        "methylumi",
        "minfi"
    ],
    "ASpli": [
        "Gviz",
        "VariantAnnotation",
        "biovizBase"
    ],
    "ATACCoGAPS": [
        "TFBSTools",
        "chromVAR",
        "motifmatchr"
    ],
    "ATACseqQC": [
        "ChIPpeakAnno",
        "TFBSTools",
        "motifStack"
    ],
    "ATACseqTFEA": [
        "TFBSTools",
        "motifmatchr"
    ],
    "atSNP": [
        "TFBSTools",
        "motifStack"
    ],
    "BadRegionFinder": [
        "VariantAnnotation"
    ],
    "BBCAnalyzer": [
        "VariantAnnotation"
    ],
    "bigmelon": [
        "lumi",
        "methylumi",
        "minfi",
        "wateRmelon"
    ],
    "biomvRCNS": [
        "Gviz",
        "VariantAnnotation",
        "biovizBase"
    ],
    "biovizBase": [
        "VariantAnnotation"
    ],
    "biscuiteer": [
        "VariantAnnotation",
        "annotatr",
        "dmrseq"
    ],
    "BOBaFIT": [
        "VariantAnnotation",
        "biovizBase",
        "ggbio"
    ],
    "borealis": [
        "DSS"
    ],
    "brainflowprobes": [
        "GenomicFiles",
        "VariantAnnotation",
        "biovizBase",
        "derfinder",
        "derfinderPlot",
        "ggbio"
    ],
    "BubbleTree": [
        "VariantAnnotation",
        "biovizBase"
    ],
    "BUSpaRse": [],
    "CAFE": [
        "VariantAnnotation",
        "biovizBase",
        "ggbio"
    ],
    "CAGEfightR": [
        "GenomicFiles",
        "GenomicInteractions",
        "Gviz",
        "VariantAnnotation",
        "biovizBase"
    ],
    "cageminer": [
        "VariantAnnotation",
        "biovizBase",
        "ggbio"
    ],
    "CAGEr": [
        "CAGEfightR",
        "GenomicFiles",
        "GenomicInteractions",
        "Gviz",
        "VariantAnnotation",
        "biovizBase"
    ],
    "cardelino": [
        "VariantAnnotation"
    ],
    "cbaf": [
        "RTCGAToolbox",
        "cBioPortalData"
    ],
    "cBioPortalData": [
        "RTCGAToolbox"
    ],
    "CexoR": [],
    "ChAMP": [
        "DMRcate",
        "Gviz",
        "VariantAnnotation",
        "biovizBase",
        "lumi",
        "methylumi",
        "minfi",
        "missMethyl",
        "wateRmelon"
    ],
    "chimeraviz": [
        "Gviz",
        "VariantAnnotation",
        "biovizBase"
    ],
    "ChIPexoQual": [
        "VariantAnnotation",
        "biovizBase"
    ],
    "ChIPpeakAnno": [],
    "ChIPQC": [
        "DiffBind"
    ],
    "chromVAR": [
        "TFBSTools"
    ],
    "cicero": [
        "Gviz",
        "VariantAnnotation",
        "biovizBase",
        "monocle"
    ],
    "circRNAprofiler": [
        "VariantAnnotation",
        "gwascat"
    ],
    "CircSeqAlignTk": [
        "Rhisat2"
    ],
    "clipper": [],
    "cliqueMS": [],
    "CNVrd2": [
        "VariantAnnotation"
    ],
    "COCOA": [
        "MIRA"
    ],
    "comapr": [
        "Gviz",
        "VariantAnnotation",
        "biovizBase"
    ],
    "coMET": [
        "Gviz",
        "VariantAnnotation",
        "biovizBase"
    ],
    "coMethDMR": [],
    "compEpiTools": [
        "Gviz",
        "VariantAnnotation",
        "biovizBase",
        "methylPipe"
    ],
    "consensusDE": [],
    "conumee": [
        "minfi"
    ],
    "crisprDesign": [
        "VariantAnnotation"
    ],
    "crisprseekplus": [
        "ChIPpeakAnno",
        "GUIDEseq"
    ],
    "crisprVerse": [
        "Gviz",
        "VariantAnnotation",
        "biovizBase",
        "crisprDesign",
        "crisprViz"
    ],
    "crisprViz": [
        "Gviz",
        "VariantAnnotation",
        "biovizBase",
        "crisprDesign"
    ],
    "cummeRbund": [
        "Gviz",
        "VariantAnnotation",
        "biovizBase"
    ],
    "dagLogo": [
        "TFBSTools",
        "motifStack"
    ],
    "DAMEfinder": [
        "VariantAnnotation"
    ],
    "decompTumor2Sig": [
        "VariantAnnotation"
    ],
    "deepSNV": [
        "VariantAnnotation"
    ],
    "DeMixT": [
        "DSS"
    ],
    "demuxSNP": [
        "VariantAnnotation"
    ],
    "derfinder": [
        "GenomicFiles",
        "VariantAnnotation"
    ],
    "derfinderPlot": [
        "GenomicFiles",
        "VariantAnnotation",
        "biovizBase",
        "derfinder",
        "ggbio"
    ],
    "DEScan2": [
        "ChIPpeakAnno"
    ],
    "DiffBind": [],
    "diffUTR": [],
    "DMRcate": [
        "Gviz",
        "VariantAnnotation",
        "biovizBase",
        "methylumi",
        "minfi",
        "missMethyl"
    ],
    "dmrseq": [
        "annotatr"
    ],
    "DominoEffect": [
        "VariantAnnotation"
    ],
    "drugTargetInteractions": [],
    "DSS": [],
    "ELMER": [
        "Gviz",
        "VariantAnnotation",
        "biovizBase"
    ],
    "enhancerHomologSearch": [
        "TFBSTools",
        "motifmatchr"
    ],
    "ENmix": [
        "minfi"
    ],
    "enrichTF": [
        "TFBSTools",
        "motifmatchr"
    ],
    "ensemblVEP": [
        "VariantAnnotation"
    ],
    "epialleleR": [
        "VariantAnnotation"
    ],
    "EpiCompare": [],
    "epigraHMM": [],
    "epimutacions": [
        "Gviz",
        "VariantAnnotation",
        "biovizBase",
        "minfi"
    ],
    "epivizr": [
        "epivizrData"
    ],
    "epivizrChart": [
        "epivizrData"
    ],
    "epivizrData": [],
    "epivizrStandalone": [
        "epivizr",
        "epivizrData"
    ],
    "erma": [
        "GenomicFiles",
        "VariantAnnotation"
    ],
    "esATAC": [
        "TFBSTools",
        "motifmatchr"
    ],
    "ExperimentHubData": [
        "AnnotationHubData"
    ],
    "extraChIPs": [
        "GenomicInteractions",
        "Gviz",
        "VariantAnnotation",
        "biovizBase"
    ],
    "fCCAC": [],
    "fcScan": [
        "VariantAnnotation"
    ],
    "ffpe": [
        "lumi",
        "methylumi",
        "minfi"
    ],
    "FLAMES": [
        "VariantAnnotation",
        "biovizBase",
        "ggbio"
    ],
    "funtooNorm": [
        "minfi"
    ],
    "GA4GHclient": [
        "VariantAnnotation"
    ],
    "GA4GHshiny": [
        "GA4GHclient",
        "VariantAnnotation"
    ],
    "GARS": [],
    "gDNAx": [
        "GenomicFiles",
        "VariantAnnotation"
    ],
    "GeneStructureTools": [
        "Gviz",
        "VariantAnnotation",
        "biovizBase"
    ],
    "GenomicFiles": [
        "VariantAnnotation"
    ],
    "GenomicInteractions": [
        "Gviz",
        "VariantAnnotation",
        "biovizBase"
    ],
    "GenomicOZone": [
        "VariantAnnotation",
        "biovizBase",
        "ggbio"
    ],
    "GenomicPlot": [
        "RCAS"
    ],
    "GenVisR": [
        "VariantAnnotation"
    ],
    "ggbio": [
        "VariantAnnotation",
        "biovizBase"
    ],
    "gmapR": [
        "VariantAnnotation"
    ],
    "GNOSIS": [
        "RTCGAToolbox",
        "cBioPortalData"
    ],
    "GRaNIE": [],
    "GSReg": [],
    "GUIDEseq": [
        "ChIPpeakAnno"
    ],
    "Gviz": [
        "VariantAnnotation",
        "biovizBase"
    ],
    "gwascat": [
        "VariantAnnotation"
    ],
    "gwasurvivr": [
        "VariantAnnotation"
    ],
    "HelloRanges": [
        "VariantAnnotation"
    ],
    "HiCDCPlus": [
        "GenomicInteractions",
        "Gviz",
        "VariantAnnotation",
        "biovizBase"
    ],
    "hiReadsProcessor": [],
    "HTSeqGenie": [
        "VariantAnnotation",
        "VariantTools",
        "gmapR"
    ],
    "icetea": [
        "VariantAnnotation"
    ],
    "iCheck": [
        "lumi",
        "methylumi",
        "minfi"
    ],
    "iCNV": [],
    "igvR": [
        "VariantAnnotation"
    ],
    "iNETgrate": [
        "minfi"
    ],
    "InPAS": [],
    "intansv": [
        "VariantAnnotation",
        "biovizBase",
        "ggbio"
    ],
    "IntEREst": [
        "GenomicFiles",
        "VariantAnnotation"
    ],
    "IsoformSwitchAnalyzeR": [
        "tximeta"
    ],
    "karyoploteR": [
        "VariantAnnotation",
        "biovizBase"
    ],
    "katdetectr": [
        "VariantAnnotation"
    ],
    "kissDE": [
        "DSS"
    ],
    "lineagespot": [
        "VariantAnnotation"
    ],
    "lumi": [
        "methylumi",
        "minfi"
    ],
    "MADSEQ": [
        "VariantAnnotation"
    ],
    "MAGAR": [
        "RnBeads",
        "methylumi",
        "minfi"
    ],
    "maser": [
        "Gviz",
        "VariantAnnotation",
        "biovizBase"
    ],
    "MatrixRider": [
        "TFBSTools"
    ],
    "mCSEA": [
        "Gviz",
        "VariantAnnotation",
        "biovizBase"
    ],
    "MEAL": [
        "Gviz",
        "VariantAnnotation",
        "biovizBase",
        "methylumi",
        "minfi",
        "missMethyl"
    ],
    "MEAT": [
        "lumi",
        "methylumi",
        "minfi",
        "wateRmelon"
    ],
    "memes": [],
    "MetaboSignal": [],
    "metagene": [],
    "metaseqR2": [
        "DSS"
    ],
    "methrix": [],
    "MethylAid": [
        "minfi"
    ],
    "methylCC": [
        "minfi"
    ],
    "methylclock": [
        "AnnotationHubData",
        "ExperimentHubData",
        "minfi"
    ],
    "methylGSA": [
        "methylumi",
        "minfi",
        "missMethyl"
    ],
    "methylPipe": [
        "Gviz",
        "VariantAnnotation",
        "biovizBase"
    ],
    "methylSig": [
        "DSS"
    ],
    "methylumi": [
        "minfi"
    ],
    "MineICA": [
        "lumi",
        "methylumi",
        "minfi"
    ],
    "minfi": [],
    "MinimumDistance": [
        "VanillaICE"
    ],
    "MIRA": [],
    "missMethyl": [
        "methylumi",
        "minfi"
    ],
    "mitoClone2": [
        "VariantAnnotation",
        "deepSNV"
    ],
    "monaLisa": [
        "TFBSTools"
    ],
    "monocle": [],
    "Motif2Site": [],
    "motifbreakR": [
        "Gviz",
        "TFBSTools",
        "VariantAnnotation",
        "biovizBase",
        "motifStack"
    ],
    "motifmatchr": [
        "TFBSTools"
    ],
    "motifStack": [
        "TFBSTools"
    ],
    "msgbsR": [
        "VariantAnnotation",
        "biovizBase",
        "ggbio"
    ],
    "multicrispr": [
        "VariantAnnotation",
        "biovizBase",
        "karyoploteR"
    ],
    "MungeSumstats": [
        "VariantAnnotation"
    ],
    "musicatk": [
        "VariantAnnotation",
        "decompTumor2Sig"
    ],
    "myvariant": [
        "VariantAnnotation"
    ],
    "NADfinder": [
        "ATACseqQC",
        "ChIPpeakAnno",
        "Gviz",
        "TFBSTools",
        "VariantAnnotation",
        "biovizBase",
        "motifStack",
        "trackViewer"
    ],
    "NanoMethViz": [],
    "netZooR": [
        "minfi",
        "quantro",
        "yarn"
    ],
    "octad": [],
    "OGRE": [
        "Gviz",
        "VariantAnnotation",
        "biovizBase"
    ],
    "OMICsPCA": [
        "HelloRanges",
        "VariantAnnotation"
    ],
    "omicsViewer": [],
    "pageRank": [
        "TFBSTools",
        "motifmatchr"
    ],
    "periodicDNA": [],
    "phemd": [
        "monocle"
    ],
    "PING": [
        "Gviz",
        "VariantAnnotation",
        "biovizBase"
    ],
    "podkat": [],
    "preciseTAD": [],
    "primirTSS": [
        "Gviz",
        "TFBSTools",
        "VariantAnnotation",
        "biovizBase"
    ],
    "profileplyr": [],
    "proteasy": [],
    "ProteoDisco": [
        "VariantAnnotation"
    ],
    "psichomics": [
        "GenomicFiles",
        "VariantAnnotation",
        "derfinder",
        "recount"
    ],
    "PureCN": [
        "VariantAnnotation"
    ],
    "Pviz": [
        "Gviz",
        "VariantAnnotation",
        "biovizBase"
    ],
    "quantro": [
        "minfi"
    ],
    "QuasR": [
        "GenomicFiles",
        "VariantAnnotation"
    ],
    "R3CPET": [
        "VariantAnnotation",
        "biovizBase",
        "ggbio"
    ],
    "R453Plus1Toolbox": [
        "VariantAnnotation"
    ],
    "raer": [],
    "RAIDS": [
        "VariantAnnotation"
    ],
    "RareVariantVis": [
        "VariantAnnotation"
    ],
    "RCAS": [],
    "recount": [
        "GenomicFiles",
        "VariantAnnotation",
        "derfinder"
    ],
    "recountmethylation": [
        "minfi"
    ],
    "REDseq": [
        "ChIPpeakAnno"
    ],
    "regioneReloaded": [],
    "regionReport": [
        "GenomicFiles",
        "VariantAnnotation",
        "derfinder"
    ],
    "regutools": [
        "Gviz",
        "VariantAnnotation",
        "biovizBase"
    ],
    "REMP": [
        "minfi"
    ],
    "ReportingTools": [
        "VariantAnnotation",
        "biovizBase",
        "ggbio"
    ],
    "RgnTX": [],
    "Rhisat2": [],
    "RiboCrypt": [],
    "RiboProfiling": [
        "VariantAnnotation",
        "biovizBase",
        "ggbio"
    ],
    "ribosomeProfilingQC": [
        "TFBSTools",
        "motifStack"
    ],
    "RIPAT": [
        "VariantAnnotation",
        "biovizBase",
        "karyoploteR"
    ],
    "RITAN": [],
    "RLSeq": [],
    "RNAAgeCalc": [
        "GenomicFiles",
        "VariantAnnotation",
        "derfinder",
        "recount"
    ],
    "rnaEditr": [],
    "RNAmodR": [
        "Gviz",
        "VariantAnnotation",
        "biovizBase"
    ],
    "RNAmodR.AlkAnilineSeq": [
        "Gviz",
        "RNAmodR",
        "VariantAnnotation",
        "biovizBase"
    ],
    "RNAmodR.ML": [
        "Gviz",
        "RNAmodR",
        "VariantAnnotation",
        "biovizBase"
    ],
    "RNAmodR.RiboMethSeq": [
        "Gviz",
        "RNAmodR",
        "VariantAnnotation",
        "biovizBase"
    ],
    "RnaSeqSampleSize": [
        "GenomicFiles",
        "VariantAnnotation",
        "derfinder",
        "recount"
    ],
    "RnBeads": [
        "methylumi",
        "minfi"
    ],
    "Rqc": [
        "GenomicFiles",
        "VariantAnnotation",
        "biovizBase"
    ],
    "RTCGAToolbox": [],
    "saseR": [
        "ASpli",
        "Gviz",
        "VariantAnnotation",
        "biovizBase"
    ],
    "scanMiR": [],
    "scanMiRApp": [
        "scanMiR"
    ],
    "scFeatures": [],
    "scmeth": [
        "annotatr"
    ],
    "scone": [],
    "SCOPE": [],
    "scoreInvHap": [
        "VariantAnnotation"
    ],
    "scruff": [
        "VariantAnnotation",
        "biovizBase",
        "ggbio"
    ],
    "scTreeViz": [
        "epivizr",
        "epivizrData"
    ],
    "segmenter": [],
    "selectKSigs": [],
    "seqArchR": [],
    "seqArchRplus": [
        "seqArchR"
    ],
    "seqCAT": [
        "VariantAnnotation"
    ],
    "shinyepico": [
        "minfi"
    ],
    "shinyMethyl": [
        "minfi"
    ],
    "signeR": [
        "VariantAnnotation"
    ],
    "signifinder": [],
    "SigsPack": [
        "VariantAnnotation"
    ],
    "SingleMoleculeFootprinting": [
        "GenomicFiles",
        "QuasR",
        "VariantAnnotation"
    ],
    "skewr": [
        "lumi",
        "methylumi",
        "minfi",
        "wateRmelon"
    ],
    "SNPhood": [
        "VariantAnnotation"
    ],
    "SomaticSignatures": [
        "VariantAnnotation",
        "biovizBase",
        "ggbio"
    ],
    "SOMNiBUS": [
        "annotatr"
    ],
    "SparseSignatures": [],
    "spatzie": [
        "GenomicInteractions",
        "Gviz",
        "TFBSTools",
        "VariantAnnotation",
        "biovizBase",
        "motifmatchr"
    ],
    "spiky": [],
    "SpliceWiz": [],
    "SPLINTER": [
        "Gviz",
        "VariantAnnotation",
        "biovizBase"
    ],
    "srnadiff": [
        "Gviz",
        "VariantAnnotation",
        "biovizBase"
    ],
    "standR": [],
    "StructuralVariantAnnotation": [
        "VariantAnnotation"
    ],
    "svaNUMT": [
        "StructuralVariantAnnotation",
        "VariantAnnotation"
    ],
    "svaRetro": [
        "StructuralVariantAnnotation",
        "VariantAnnotation"
    ],
    "tadar": [
        "Gviz",
        "VariantAnnotation",
        "biovizBase"
    ],
    "TAPseq": [],
    "terraTCGAdata": [],
    "TFBSTools": [],
    "TFHAZ": [],
    "TitanCNA": [
        "VariantAnnotation"
    ],
    "tLOH": [
        "VariantAnnotation"
    ],
    "trackViewer": [
        "Gviz",
        "VariantAnnotation",
        "biovizBase"
    ],
    "transite": [],
    "tRNAscanImport": [],
    "TVTB": [
        "Gviz",
        "VariantAnnotation",
        "biovizBase",
        "ensemblVEP"
    ],
    "tximeta": [],
    "Ularcirc": [],
    "UMI4Cats": [],
    "uncoverappLib": [
        "Gviz",
        "VariantAnnotation",
        "biovizBase"
    ],
    "Uniquorn": [
        "VariantAnnotation"
    ],
    "uSORT": [
        "monocle"
    ],
    "VanillaICE": [],
    "VarCon": [],
    "VariantAnnotation": [],
    "VariantFiltering": [
        "Gviz",
        "VariantAnnotation",
        "biovizBase"
    ],
    "VariantTools": [
        "VariantAnnotation"
    ],
    "VCFArray": [
        "GenomicFiles",
        "VariantAnnotation"
    ],
    "vtpnet": [
        "VariantAnnotation",
        "gwascat"
    ],
    "vulcan": [
        "ChIPpeakAnno",
        "DiffBind"
    ],
    "wateRmelon": [
        "lumi",
        "methylumi",
        "minfi"
    ],
    "XNAString": [],
    "YAPSA": [
        "SomaticSignatures",
        "VariantAnnotation",
        "biovizBase",
        "ggbio"
    ],
    "yarn": [
        "minfi",
        "quantro"
    ],
    "ZygosityPredictor": [
        "VariantAnnotation"
    ]
}